{
  "version": "7",
  "dialect": "postgresql",
  "entries": [
    {
      "idx": 0,
      "version": "7",
      "when": 1755969623871,
      "tag": "0000_daffy_venus",
      "breakpoints": true
    },
    {
      "idx": 1,
      "version": "7",
      "when": 1755969737371,
      "tag": "0001_first_riptide",
      "breakpoints": true
    },
    {
      "idx": 2,
      "version": "7",
      "when": 1755969788681,
      "tag": "0002_gigantic_norman_osborn",
      "breakpoints": true
    },
    {
      "idx": 3,
      "version": "7",
      "when": 1756004468714,
      "tag": "0003_quick_betty_ross",
      "breakpoints": true
    },
    {
      "idx": 4,
      "version": "7",
      "when": 1756005715223,
      "tag": "0004_lonely_ronan",
      "breakpoints": true
    }
  ]
}